science_calc/Calculator.py
science_calc/__init__.py
science_calc/main.py
science_calc-0.1.2.dist-info/METADATA
science_calc-0.1.2.dist-info/WHEEL
science_calc-0.1.2.dist-info/entry_points.txt
science_calc-0.1.2.dist-info/licenses/LICENSE
science_calc-0.1.2.dist-info/RECORD
