Metadata-Version: 2.4
Name: science-calc
Version: 0.1.2
Summary: A sleek, powerful Scientific Calculator with a modern TUI.
Author: Mahir29Flame
License-File: LICENSE
Requires-Python: >=3.8
Requires-Dist: textual>=0.86.0
